agentrouter/__init__.py
agentrouter/config.py
agentrouter/exceptions.py
agentrouter/types.py
agentrouter/agents/__init__.py
agentrouter/agents/base.py
agentrouter/agents/manager.py
agentrouter/agents/worker.py
agentrouter/api/__init__.py
agentrouter/api/base.py
agentrouter/api/plan_api.py
agentrouter/api/tool_call_api.py
agentrouter/api/utility_api.py
agentrouter/plugins/__init__.py
agentrouter/plugins/base.py
agentrouter/plugins/registry.py
agentrouter/tools/__init__.py
agentrouter/tools/decorator.py
agentrouter/tools/executor.py
agentrouter/tools/registry.py
agentrouter/utils/__init__.py
agentrouter/utils/error_formatter.py
agentrouter/utils/logging.py
agentrouter/utils/message_transformer.py
agentrouter/utils/openai_integration.py
agentrouter/validators/__init__.py
agentrouter/validators/format_validators.py
agentrouter/validators/message_flow.py
agentrouter/visualization/__init__.py
agentrouter/visualization/pipeline_inspector.py
agentrouter/visualization/tracer.py
agentrouter/visualization/visualizer.py
agentrouter-0.0.1b12.dist-info/licenses/LICENSE
agentrouter-0.0.1b12.dist-info/METADATA
agentrouter-0.0.1b12.dist-info/WHEEL
agentrouter-0.0.1b12.dist-info/entry_points.txt
agentrouter-0.0.1b12.dist-info/top_level.txt
agentrouter-0.0.1b12.dist-info/RECORD
