Metadata-Version: 2.4
Name: agentrouter
Version: 0.0.1b12
Summary: Simplify the Complex, Amplify the Intelligent for Enterprise. Orchestrate multiple agents with ease: register agents, integrate tools, define custom instructions, and leverage multiple models.
Home-page: https://agents-docs.us.inc
Author: AgentRouter Team
Author-email: AgentRouter Team <support@us.inc>
Maintainer-email: AgentRouter Team <support@us.inc>
License: Non-Commercial Evaluation License
Project-URL: Homepage, https://agents-docs.us.inc
Project-URL: Documentation, https://agents-docs.us.inc/docs/quickstart
Keywords: agents,multi-agent,ai,llm,orchestration,workflow,automation
Classifier: Development Status :: 3 - Alpha
Classifier: Intended Audience :: Developers
Classifier: License :: Other/Proprietary License
Classifier: Programming Language :: Python :: 3
Classifier: Programming Language :: Python :: 3.8
Classifier: Programming Language :: Python :: 3.9
Classifier: Programming Language :: Python :: 3.10
Classifier: Programming Language :: Python :: 3.11
Classifier: Programming Language :: Python :: 3.12
Classifier: Topic :: Software Development :: Libraries :: Python Modules
Classifier: Topic :: Scientific/Engineering :: Artificial Intelligence
Requires-Python: >=3.8
License-File: LICENSE
Requires-Dist: httpx>=0.24.0
Requires-Dist: pydantic>=2.0.0
Requires-Dist: asyncio-throttle>=1.0.2
Requires-Dist: typing-extensions>=4.7.0
Requires-Dist: python-dateutil>=2.8.2
Requires-Dist: openai>=1.0.0
Requires-Dist: jsonschema>=4.18.0
Requires-Dist: orjson>=3.9.0
Requires-Dist: aiofiles>=23.0.0
Requires-Dist: aiodns>=3.0.0
Requires-Dist: structlog>=23.1.0
Requires-Dist: rich>=13.5.0
Requires-Dist: python-dotenv>=1.0.0
Requires-Dist: pyyaml>=6.0.1
Requires-Dist: tenacity>=8.2.0
Requires-Dist: backoff>=2.2.0
Requires-Dist: cachetools>=5.3.0
Requires-Dist: validators>=0.20.0
Provides-Extra: dev
Requires-Dist: pytest>=7.4.0; extra == "dev"
Requires-Dist: pytest-asyncio>=0.21.0; extra == "dev"
Requires-Dist: pytest-cov>=4.1.0; extra == "dev"
Requires-Dist: black>=23.0.0; extra == "dev"
Requires-Dist: isort>=5.12.0; extra == "dev"
Requires-Dist: flake8>=6.0.0; extra == "dev"
Requires-Dist: mypy>=1.4.0; extra == "dev"
Requires-Dist: sphinx>=7.0.0; extra == "dev"
Dynamic: author
Dynamic: home-page
Dynamic: license-file
Dynamic: requires-python
